{
  "$schema": "https://mintlify.com/docs.json",
  "name": "Image to Alpha Pattern",
  "theme": "palm",
  "colors": {
    "primary": "#6366f1",
    "light": "#e0e7ff",
    "dark": "#1e1b4b"
  },
  "navbar": {
    "primary": {
      "type": "github",
      "href": "https://github.com/tobiasvnicolas/ImageToAlphaPattern"
    }
  },
  "footer": {
    "socials": {
      "github": "https://github.com/tobiasvnicolas/ImageToAlphaPattern"
    }
  },
  "navigation": {
    "tabs": [
      {
        "tab": "Documentation",
        "groups": [
          {
            "group": "Get Started",
            "pages": ["introduction", "quickstart"]
          },
          {
            "group": "Using the App",
            "pages": [
              "guides/upload-image",
              "guides/configure-matrix",
              "guides/color-filters",
              "guides/preview-and-edit",
              "guides/export"
            ]
          },
          {
            "group": "Reference",
            "pages": [
              "reference/image-processing",
              "reference/export-formats",
              "reference/keyboard-shortcuts"
            ]
          }
        ]
      }
    ]
  }
}
